lag/__init__.py
lag-0.0.3.dist-info/LICENSE
lag-0.0.3.dist-info/METADATA
lag-0.0.3.dist-info/WHEEL
lag-0.0.3.dist-info/top_level.txt
lag-0.0.3.dist-info/RECORD
