Metadata-Version: 2.1
Name: lag
Version: 0.0.3
Summary: Performance gauging tools
Home-page: https://github.com/thorwhalen/lag
Author: Thor Whalen
License: mit
Platform: any
